zac/Two_NN.py
zac/__init__.py
zac/atmo_solver.py
zac/create_logger.py
zac/create_training_set.py
zac/downloaders.py
zac/get_MCD43.py
zac/kernels.py
zac/lhd.py
zac/modis_tile_cal.py
zac/multi_process.py
zac/psf_optimize.py
zac/raster_boundary.py
zac/reproject.py
zac/smoothn.py
zac/the_aerosol.py
zac/the_correction.py
zac-0.1.0.dist-info/WHEEL
zac-0.1.0.dist-info/METADATA
zac-0.1.0.dist-info/RECORD
